arimastate/__init__.py
arimastate/model.py
arimastate-0.0.3.dist-info/LICENCE
arimastate-0.0.3.dist-info/METADATA
arimastate-0.0.3.dist-info/WHEEL
arimastate-0.0.3.dist-info/top_level.txt
arimastate-0.0.3.dist-info/RECORD
