Metadata-Version: 2.1
Name: arimastate
Version: 0.0.3
Summary: python module for state space formulation of arima models
Home-page: https://github.com/xiaoras/arimastate
Author: Andrea Dapor
Author-email: andrea.dapor@gmail.com
License: UNKNOWN
Platform: UNKNOWN
Classifier: Programming Language :: Python :: 3
Classifier: License :: OSI Approved :: MIT License
Classifier: Operating System :: OS Independent
Requires-Python: >=3.6
Requires-Dist: numpy
Requires-Dist: scipy
Requires-Dist: sympy
